{
  "name": "code-editor-demo",
  "files": [
    {
      "name": "code-editor-demo.tsx",
      "content": "import { CodeEditor } from \"@/registry/default/ui/code-editor\"\n\nexport default function CodeEditorDemo() {\n  return (\n    <CodeEditor\n      defaultValue={`function fibonacci(n) {\n  if (n <= 1) return n\n\n  return fibonacci(n - 1) + fibonacci(n - 2)\n}\n\n// Calculate the 10th Fibonacci number\nconst result = fibonacci(10)\nconsole.log(\\`The 10th Fibonacci number is: \\${result}\\`)`}\n      language=\"javascript\"\n      height=\"300px\"\n    />\n  )\n}\n"
    }
  ],
  "type": "components:example"
}